outlook_mail_loader/__init__.py
outlook_mail_loader/class_mail_dumper.py
outlook_mail_loader/class_mail_getter.py
outlook_mail_loader/class_outlook_message.py
outlook_mail_loader/exceptions.py
outlook_mail_loader/logger.py
outlook_mail_loader/mail_listener.py
outlook_mail_loader/other.py
outlook_mail_loader/recursive.py
outlook_mail_loader/tbd_class_mail_listener.py
outlook_mail_loader-0.1.9.dist-info/AUTHORS.rst
outlook_mail_loader-0.1.9.dist-info/LICENSE.txt
outlook_mail_loader-0.1.9.dist-info/METADATA
outlook_mail_loader-0.1.9.dist-info/WHEEL
outlook_mail_loader-0.1.9.dist-info/top_level.txt
outlook_mail_loader-0.1.9.dist-info/RECORD
