Metadata-Version: 2.1
Name: outlook-mail-loader
Version: 0.1.9
Summary: This library helps to dump letters from outlook to some local folder in human readable format.
Home-page: https://github.com/stas-prokopiev/outlook_mail_loader
Author: stanislav prokopyev
Author-email: stas.prokopiev@gmail.com
License: mit
Platform: any
Classifier: Development Status :: 4 - Beta
Classifier: Programming Language :: Python
Classifier: Operating System :: OS Independent
Classifier: License :: OSI Approved :: MIT License
Classifier: Programming Language :: Python :: 3
Classifier: Programming Language :: Python :: 3.6
Classifier: Programming Language :: Python :: 3.7
Classifier: Programming Language :: Python :: 3.8
Classifier: Programming Language :: Python :: 3.9
Requires-Dist: pywin32
Requires-Dist: python-dateutil
Requires-Dist: tqdm
Requires-Dist: logging-nice-handlers
Requires-Dist: char
Requires-Dist: local-simple-database
Provides-Extra: testing
Requires-Dist: pytest ; extra == 'testing'
Requires-Dist: pytest-cov ; extra == 'testing'
